crystalaudio/__init__.py
crystalaudio/crystalaudio.py
crystalaudio-1.0.2.dist-info/LICENSE.txt
crystalaudio-1.0.2.dist-info/METADATA
crystalaudio-1.0.2.dist-info/WHEEL
crystalaudio-1.0.2.dist-info/RECORD
