Metadata-Version: 2.1
Name: crystalaudio
Version: 1.0.2
Summary: CrystalPlay("file.wav")
License: LICENSE.txt
Author: 3verlaster
Author-email: ndizhevskij@gmail.com
Requires-Python: >=3.6,<4.0
Classifier: License :: Other/Proprietary License
Classifier: Programming Language :: Python :: 3
Classifier: Programming Language :: Python :: 3.6
Classifier: Programming Language :: Python :: 3.7
Classifier: Programming Language :: Python :: 3.8
Classifier: Programming Language :: Python :: 3.9
Classifier: Programming Language :: Python :: 3.10
Classifier: Programming Language :: Python :: 3.11
